perplexity/__init__.py
perplexity/tools/__init__.py
perplexity/tools/perplexity_api_tool.py
perplexity/tools/utils.py
perplexity/yamls/perplexity_api_tool.yaml
tests/__init__.py
tests/test_perplexity_api_tool.py
perplexity_api_tool-0.0.1.dist-info/METADATA
perplexity_api_tool-0.0.1.dist-info/WHEEL
perplexity_api_tool-0.0.1.dist-info/entry_points.txt
perplexity_api_tool-0.0.1.dist-info/top_level.txt
perplexity_api_tool-0.0.1.dist-info/RECORD
