Metadata-Version: 2.1
Name: perplexity_api_tool
Version: 0.0.1
Summary: This is perplexity response tool
